workflows/__init__.py
workflows/errors.py
workflows/file_task.py
workflows/task.py
py_workflows-0.1.21.dist-info/METADATA
py_workflows-0.1.21.dist-info/WHEEL
py_workflows-0.1.21.dist-info/top_level.txt
py_workflows-0.1.21.dist-info/RECORD
