Metadata-Version: 2.1
Name: py-workflows
Version: 0.1.21
Summary: A workflow management library
Home-page: UNKNOWN
Author: Bao Wei
Author-email: baowei.ur521@gmail.com
License: MIT
Platform: UNKNOWN
Requires-Python: >=3.8
Requires-Dist: atomic-write-path (>=1.4)
Requires-Dist: python-dateutil (>=2.8)
